textual_cookbook/__init__.py
textual_cookbook/common_bugs/bug_get_screen.py
textual_cookbook/common_bugs/bug_query_screens.py
textual_cookbook/common_bugs/bug_same_widget.py
textual_cookbook/common_bugs/bug_widget_css.py
textual_cookbook/main.py
textual_cookbook/recipes/animation_effects/animate_multiple.py
textual_cookbook/recipes/animation_effects/animate_offset.py
textual_cookbook/recipes/animation_effects/context_menu.py
textual_cookbook/recipes/animation_effects/reveal_redacted.py
textual_cookbook/recipes/animation_effects/spinner_widget.py
textual_cookbook/recipes/animation_effects/spinner_widget_loading.py
textual_cookbook/recipes/architecture_patterns/abc_meta.py
textual_cookbook/recipes/architecture_patterns/app_dict.py
textual_cookbook/recipes/architecture_patterns/config.ini
textual_cookbook/recipes/architecture_patterns/configparser_usage.py
textual_cookbook/recipes/architecture_patterns/css_basics.py
textual_cookbook/recipes/architecture_patterns/help_screen.py
textual_cookbook/recipes/architecture_patterns/logging_html.py
textual_cookbook/recipes/modifying_widgets/datatable_expandcol.py
textual_cookbook/recipes/modifying_widgets/datatable_headersort.py
textual_cookbook/recipes/modifying_widgets/header_timezone.py
textual_cookbook/recipes/modifying_widgets/listview_tooltips.py
textual_cookbook/recipes/modifying_widgets/progress_bounce.py
textual_cookbook/recipes/modifying_widgets/tabs_unclickable.py
textual_cookbook/recipes/modifying_widgets/textarea_submit.py
textual_cookbook/recipes/styling_and_colors/button_focus_highlight.py
textual_cookbook/recipes/styling_and_colors/button_markup.py
textual_cookbook/recipes/styling_and_colors/checkbox_style.py
textual_cookbook/recipes/styling_and_colors/collapsible_style.py
textual_cookbook/recipes/styling_and_colors/color_basic.py
textual_cookbook/recipes/styling_and_colors/logging_color.py
textual_cookbook/recipes/textual_api_usage/app_events_order.py
textual_cookbook-0.2.0.dist-info/licenses/LICENSE
textual_cookbook-0.2.0.dist-info/WHEEL
textual_cookbook-0.2.0.dist-info/entry_points.txt
textual_cookbook-0.2.0.dist-info/METADATA
textual_cookbook-0.2.0.dist-info/RECORD
