Metadata-Version: 2.4
Name: textual-cookbook
Version: 0.2.0
Summary: Textual Cookbook: Recipes for Textual Applications
Keywords: python,textual,tui,cookbook
Author: edward-jazzhands
Author-email: edward-jazzhands <ed.jazzhands@gmail.com>
License-Expression: MIT
License-File: LICENSE
Classifier: Development Status :: 3 - Alpha
Classifier: License :: OSI Approved :: MIT License
Classifier: Operating System :: OS Independent
Classifier: Programming Language :: Python
Classifier: Programming Language :: Python :: 3.10
Classifier: Programming Language :: Python :: 3.11
Classifier: Programming Language :: Python :: 3.12
Classifier: Programming Language :: Python :: 3.13
Classifier: Programming Language :: Python :: 3 :: Only
Requires-Dist: textual[syntax]>=5.3.0
Requires-Dist: textual-pyfiglet>=1.1.0
Requires-Dist: pytest-json-report>=1.5.0
Requires-Python: >=3.10
Project-URL: Changelog, https://github.com/ttygroup/textual-cookbook/blob/master/CHANGELOG.md
Project-URL: Repository, https://github.com/ttygroup/textual-cookbook
